examscanuiuc
