Metadata-Version: 1.0
Name: examscanuiuc
Version: 0.0.4
Summary: For added tags to and processing scanned exams.
Home-page: https://bitbucket.org/Mark_Bell/examscanuiuc
Author: Mark Bell
Author-email: mcbell@illinois.edu
License: UNKNOWN
Platform: UNKNOWN
